CHANGES.rst
CONTRIBUTORS.rst
MANIFEST.in
README.rst
bootstrap.sh
setup.cfg
setup.py
docs/LICENSE.GPL
docs/LICENSE.rst
docs/index.rst
src/collective/__init__.py
src/collective.linguatags.egg-info/PKG-INFO
src/collective.linguatags.egg-info/SOURCES.txt
src/collective.linguatags.egg-info/dependency_links.txt
src/collective.linguatags.egg-info/entry_points.txt
src/collective.linguatags.egg-info/namespace_packages.txt
src/collective.linguatags.egg-info/not-zip-safe
src/collective.linguatags.egg-info/requires.txt
src/collective.linguatags.egg-info/top_level.txt
src/collective/linguatags/__init__.py
src/collective/linguatags/configure.zcml
src/collective/linguatags/interfaces.py
src/collective/linguatags/setuphandlers.py
src/collective/linguatags/storage.py
src/collective/linguatags/testing.py
src/collective/linguatags/translationdomain.py
src/collective/linguatags/browser/__init__.py
src/collective/linguatags/browser/configure.zcml
src/collective/linguatags/browser/controlpanel.pt
src/collective/linguatags/browser/controlpanel.py
src/collective/linguatags/browser/keywords.pt
src/collective/linguatags/browser/keywords.py
src/collective/linguatags/locales/collective.linguatags.pot
src/collective/linguatags/locales/update.sh
src/collective/linguatags/profiles/default/browserlayer.xml
src/collective/linguatags/profiles/default/controlpanel.xml
src/collective/linguatags/profiles/default/metadata.xml
src/collective/linguatags/profiles/uninstall/browserlayer.xml
src/collective/linguatags/tests/__init__.py
src/collective/linguatags/tests/test_setup.py
src/collective/linguatags/tests/test_translationdomain.py