Metadata-Version: 2.1
Name: collective.linguatags
Version: 2.0.1
Summary: Multilingual Keywords for Plone
Home-page: https://pypi.python.org/pypi/collective.linguatags
Author: Jens W. Klein
Author-email: jk@kleinundpartner.at
License: GPL version 2
Keywords: Python Plone
Platform: UNKNOWN
Classifier: Development Status :: 5 - Production/Stable
Classifier: Environment :: Web Environment
Classifier: Framework :: Plone
Classifier: Framework :: Plone :: 6.0
Classifier: Programming Language :: Python
Classifier: Programming Language :: Python :: 3.7
Classifier: Programming Language :: Python :: 3.8
Classifier: Programming Language :: Python :: 3.9
Classifier: Operating System :: OS Independent
Classifier: License :: OSI Approved :: GNU General Public License v2 (GPLv2)
Provides-Extra: test
